setup.py
csadipkg/__init__.py
csadipkg/calculator.py
csadipkg.egg-info/PKG-INFO
csadipkg.egg-info/SOURCES.txt
csadipkg.egg-info/dependency_links.txt
csadipkg.egg-info/top_level.txt