Metadata-Version: 2.1
Name: csadipkg
Version: 0.0.1
Summary: Chetan ADI python Package module
Home-page: https://github.com/csuresh/mydemopackage/myadipkg
Author: chetanms
Author-email: chetan4ms@gmail.com
Classifier: Programming Language :: Python :: 3
Classifier: Operating System :: OS Independent
